ZhuomianYunweiGuanliZhinanFix1/README.md
ZhuomianYunweiGuanliZhinanFix1/__init__.py
ZhuomianYunweiGuanliZhinanFix1/__main__.py
ZhuomianYunweiGuanliZhinanFix1/file.epub
ZhuomianYunweiGuanliZhinanFix1/index.html
ZhuomianYunweiGuanliZhinanFix1/css/__init__.py
ZhuomianYunweiGuanliZhinanFix1/css/annotations.css
ZhuomianYunweiGuanliZhinanFix1/css/main.css
ZhuomianYunweiGuanliZhinanFix1/css/normalize.css
ZhuomianYunweiGuanliZhinanFix1/css/popup.css
ZhuomianYunweiGuanliZhinanFix1/font/__init__.py
ZhuomianYunweiGuanliZhinanFix1/font/fontello.eot
ZhuomianYunweiGuanliZhinanFix1/font/fontello.svg
ZhuomianYunweiGuanliZhinanFix1/font/fontello.ttf
ZhuomianYunweiGuanliZhinanFix1/font/fontello.woff
ZhuomianYunweiGuanliZhinanFix1/img/__init__.py
ZhuomianYunweiGuanliZhinanFix1/img/annotator-glyph-sprite.png
ZhuomianYunweiGuanliZhinanFix1/img/annotator-icon-sprite.png
ZhuomianYunweiGuanliZhinanFix1/img/apple-touch-icon.png
ZhuomianYunweiGuanliZhinanFix1/img/cancelfullscreen.png
ZhuomianYunweiGuanliZhinanFix1/img/close.png
ZhuomianYunweiGuanliZhinanFix1/img/fullscreen.png
ZhuomianYunweiGuanliZhinanFix1/img/loader.gif
ZhuomianYunweiGuanliZhinanFix1/img/menu-icon.png
ZhuomianYunweiGuanliZhinanFix1/img/save.png
ZhuomianYunweiGuanliZhinanFix1/img/saved.png
ZhuomianYunweiGuanliZhinanFix1/img/settings-s.png
ZhuomianYunweiGuanliZhinanFix1/img/settings.png
ZhuomianYunweiGuanliZhinanFix1/img/star.png
ZhuomianYunweiGuanliZhinanFix1/js/__init__.py
ZhuomianYunweiGuanliZhinanFix1/js/epub.js
ZhuomianYunweiGuanliZhinanFix1/js/epub.min.js
ZhuomianYunweiGuanliZhinanFix1/js/epub.min.map
ZhuomianYunweiGuanliZhinanFix1/js/hooks.min.js
ZhuomianYunweiGuanliZhinanFix1/js/hooks.min.map
ZhuomianYunweiGuanliZhinanFix1/js/reader.js
ZhuomianYunweiGuanliZhinanFix1/js/reader.js.map
ZhuomianYunweiGuanliZhinanFix1/js/reader.min.js
ZhuomianYunweiGuanliZhinanFix1/js/reader.min.map
ZhuomianYunweiGuanliZhinanFix1/js/hooks/__init__.py
ZhuomianYunweiGuanliZhinanFix1/js/hooks/extensions/__init__.py
zhuomian_yunwei_guanli_zhinan_fix1-2025.3.24.2.dist-info/METADATA
zhuomian_yunwei_guanli_zhinan_fix1-2025.3.24.2.dist-info/WHEEL
zhuomian_yunwei_guanli_zhinan_fix1-2025.3.24.2.dist-info/entry_points.txt
zhuomian_yunwei_guanli_zhinan_fix1-2025.3.24.2.dist-info/top_level.txt
zhuomian_yunwei_guanli_zhinan_fix1-2025.3.24.2.dist-info/RECORD
